AUTHORS
LICENSE
poetry_publish/__init__.py
poetry_publish/publish.py
poetry_publish/self.py
poetry_publish/tests/__init__.py
poetry_publish/tests/conftest.py
poetry_publish/tests/test_assert_rst_readme.py
poetry_publish/tests/test_project_setup.py
poetry_publish/tests/test_publish.py
poetry_publish/utils/__init__.py
poetry_publish/utils/interactive.py
poetry_publish/utils/subprocess_utils.py
poetry_publish-0.4.1.dist-info/entry_points.txt
poetry_publish-0.4.1.dist-info/LICENSE
poetry_publish-0.4.1.dist-info/WHEEL
poetry_publish-0.4.1.dist-info/METADATA
poetry_publish-0.4.1.dist-info/RECORD
